auto_model/__init__.py
auto_model/lightgbmOptimizer.py
automodel/__init__.py
automodel/lightgbmOptimizer.py
automodel/logisticOptimizer.py
automodel/randomforestOptimizer.py
automodel/svmOptimizer.py
pyautomodel/__init__.py
pyautomodel/utils.py
pyautomodel/automodel/__init__.py
pyautomodel/automodel/catboostOptimizer.py
pyautomodel/automodel/lightgbmOptimizer.py
pyautomodel/automodel/logisticOptimizer.py
pyautomodel/automodel/preprocessor.py
pyautomodel/automodel/randomforestOptimizer.py
pyautomodel/automodel/svmOptimizer.py
pyautomodel/automodel/xgboostOptimizer.py
pyautomodel-0.10.5.dist-info/LICENSE
pyautomodel-0.10.5.dist-info/METADATA
pyautomodel-0.10.5.dist-info/WHEEL
pyautomodel-0.10.5.dist-info/top_level.txt
pyautomodel-0.10.5.dist-info/RECORD
